ctdb_utility_lib/__init__.py
ctdb_utility_lib/admin_utility.py
ctdb_utility_lib/utility.py
ctdb_utility_lib-0.3.7.dist-info/METADATA
ctdb_utility_lib-0.3.7.dist-info/WHEEL
ctdb_utility_lib-0.3.7.dist-info/top_level.txt
ctdb_utility_lib-0.3.7.dist-info/RECORD
