Metadata-Version: 2.1
Name: ctdb-utility-lib
Version: 0.3.7
Summary: Contact Tracer DB Utility Python library
Home-page: UNKNOWN
Author: [Ahmed, Dylan]
License: MIT
Platform: UNKNOWN
Requires-Dist: psycopg2
